pytest_xfiles.py
pytest_xfiles-0.2.0.dist-info/DESCRIPTION.rst
pytest_xfiles-0.2.0.dist-info/METADATA
pytest_xfiles-0.2.0.dist-info/RECORD
pytest_xfiles-0.2.0.dist-info/WHEEL
pytest_xfiles-0.2.0.dist-info/entry_points.txt
pytest_xfiles-0.2.0.dist-info/metadata.json
pytest_xfiles-0.2.0.dist-info/pbr.json
pytest_xfiles-0.2.0.dist-info/top_level.txt
