Metadata-Version: 2.0
Name: pytest-xfiles
Version: 0.2.0
Summary: Pytest fixtures providing data read from function, module or package related (x)files.
Home-page: https://github.com/vlcinsky/pytest_xfiles
Author: Jan Vlčinský
Author-email: jan.vlcinsky@tamtamresearch.com
License: UNKNOWN
Keywords: pytest
Requires-Dist: ruamel.yaml
Requires-Dist: pathlib; (python_version<'3.4')
Provides-Extra: yaml
Requires-Dist: pyyaml; extra == 'yaml'
